GageRnR/__init__.py
GageRnR/__main__.py
GageRnR/application.py
GageRnR/dataLoader.py
GageRnR/gageRnR.py
GageRnR/generator.py
GageRnR/linearity.py
GageRnR/normality.py
GageRnR/reportGenerator.py
GageRnR/statistics.py
GageRnR/resources/GageRnR.html
GageRnR/resources/Linearity.html
GageRnR/resources/Normality.html
GageRnR/resources/Statistics.html
GageRnR/resources/__init__.py
GageRnR/resources/bootstrap.min.css
GageRnR/tests/__init__.py
GageRnR/tests/data.py
GageRnR/tests/test_application.py
GageRnR/tests/test_dataLoader.py
GageRnR/tests/test_gaugeRnR.py
GageRnR/tests/test_generator.py
GageRnR/tests/test_linearity.py
GageRnR/tests/test_normality.py
GageRnR/tests/test_statistics.py
GageRnR-0.8.0.dist-info/LICENSE
GageRnR-0.8.0.dist-info/METADATA
GageRnR-0.8.0.dist-info/WHEEL
GageRnR-0.8.0.dist-info/entry_points.txt
GageRnR-0.8.0.dist-info/top_level.txt
GageRnR-0.8.0.dist-info/RECORD
